tests/__init__.py
tests/contextmgrs/__init__.py
tests/contextmgrs/descriptors/__init__.py
tests/emitters/__init__.py
tests/emitters/test_construct_interop.py
tests/emitters/descriptors/__init__.py
tests/emitters/descriptors/test_standard.py
tests/types/__init__.py
tests/types/test_types.py
tests/types/descriptors/__init__.py
tests/types/descriptors/test_standard.py
tests/types/descriptors/test_uac2.py
tests/types/descriptors/partial/__init__.py
tests/types/superspeed/__init__.py
usb_construct/__init__.py
usb_construct/py.typed
usb_construct/contextmgrs/__init__.py
usb_construct/contextmgrs/manager.py
usb_construct/contextmgrs/descriptors/__init__.py
usb_construct/contextmgrs/descriptors/dfu.py
usb_construct/contextmgrs/descriptors/microsoft.py
usb_construct/contextmgrs/descriptors/uac3.py
usb_construct/emitters/__init__.py
usb_construct/emitters/construct_interop.py
usb_construct/emitters/descriptor.py
usb_construct/emitters/descriptors/__init__.py
usb_construct/emitters/descriptors/cdc.py
usb_construct/emitters/descriptors/dfu.py
usb_construct/emitters/descriptors/microsoft.py
usb_construct/emitters/descriptors/standard.py
usb_construct/emitters/descriptors/uac1.py
usb_construct/emitters/descriptors/uac2.py
usb_construct/emitters/descriptors/uac3.py
usb_construct/emitters/descriptors/uas3.py
usb_construct/emitters/descriptors/webusb.py
usb_construct/types/__init__.py
usb_construct/types/descriptor.py
usb_construct/types/descriptors/__init__.py
usb_construct/types/descriptors/cdc.py
usb_construct/types/descriptors/dfu.py
usb_construct/types/descriptors/microsoft.py
usb_construct/types/descriptors/midi1.py
usb_construct/types/descriptors/midi2.py
usb_construct/types/descriptors/msc.py
usb_construct/types/descriptors/standard.py
usb_construct/types/descriptors/uac1.py
usb_construct/types/descriptors/uac2.py
usb_construct/types/descriptors/uac3.py
usb_construct/types/descriptors/uas3.py
usb_construct/types/descriptors/webusb.py
usb_construct-0.2.1.dist-info/LICENSE
usb_construct-0.2.1.dist-info/METADATA
usb_construct-0.2.1.dist-info/WHEEL
usb_construct-0.2.1.dist-info/top_level.txt
usb_construct-0.2.1.dist-info/RECORD
