Metadata-Version: 2.1
Name: usb-construct
Version: 0.2.1
Summary: python library providing utilities, data structures, constants, parsers, and tools for working with USB data
Home-page: https://usb-construct.shmdn.link/
Author: Katherine J. Temkin
Author-email: k@ktemkin.com
Maintainer: Aki Van Ness, Rachel Mant
Maintainer-email: aki@lethalbit.net, git@dragonmux.network
License: BSD-3-Clause
Project-URL: Documentation, https://usb-construct.shmdn.link/
Project-URL: Source Code, https://github.com/shrine-maiden-heavy-industries/usb-construct
Project-URL: Bug Tracker, https://github.com/shrine-maiden-heavy-industries/usb-construct/issues
Classifier: Development Status :: 4 - Beta
Classifier: Environment :: Console
Classifier: Environment :: Plugins
Classifier: Intended Audience :: Developers
Classifier: Intended Audience :: Science/Research
Classifier: License :: OSI Approved :: BSD License
Classifier: Natural Language :: English
Classifier: Operating System :: OS Independent
Classifier: Programming Language :: Python :: 3.9
Classifier: Programming Language :: Python :: 3.10
Classifier: Programming Language :: Python :: 3.11
Classifier: Topic :: Scientific/Engineering
Classifier: Topic :: Security
Classifier: Topic :: Software Development :: Libraries
Classifier: Topic :: System :: Hardware :: Universal Serial Bus (USB)
Requires-Python: ~=3.10
License-File: LICENSE
Requires-Dist: construct
Provides-Extra: dev
Requires-Dist: nox; extra == "dev"
